LICENSE
MANIFEST.in
README.md
requirements.txt
setup.py
tests/__init__.py
tests/test_api_client.py
texteripy/__init__.py
texteripy/client.py
texteripy.egg-info/PKG-INFO
texteripy.egg-info/SOURCES.txt
texteripy.egg-info/dependency_links.txt
texteripy.egg-info/requires.txt
texteripy.egg-info/top_level.txt