Metadata-Version: 2.1
Name: texteripy
Version: 0.0.2
Summary: Unofficial Texterify API client for Python
Home-page: UNKNOWN
Author: lor3m
Author-email: hiddenlorem@pm.me
License: LGPLv3
Project-URL: Source Code, https://github.com/monday4me/texteripy
Platform: UNKNOWN
Classifier: Programming Language :: Python
Classifier: Programming Language :: Python :: 3
Classifier: Programming Language :: Python :: 3.10
Classifier: Programming Language :: Python :: 3.11
Classifier: Intended Audience :: Developers
Classifier: License :: OSI Approved :: MIT License
Classifier: Operating System :: OS Independent
Classifier: Topic :: Software Development :: Libraries :: Python Modules
Classifier: Topic :: Internet
Classifier: License :: OSI Approved :: GNU Lesser General Public License v3 (LGPLv3)
Requires-Python: >=3.10
License-File: LICENSE
